CHANGELOG.txt
LICENCE.txt
MANIFEST.in
README.txt
setup.py
JAYANTBASICCALCULATOR.egg-info/PKG-INFO
JAYANTBASICCALCULATOR.egg-info/SOURCES.txt
JAYANTBASICCALCULATOR.egg-info/dependency_links.txt
JAYANTBASICCALCULATOR.egg-info/top_level.txt
JayantBasicCalculator/CHANGELOG.txt
JayantBasicCalculator/LICENCE.txt
JayantBasicCalculator/README.txt
JayantBasicCalculator/__init__.py
JayantBasicCalculator/setup.py